<?xml version='1.0' encoding='utf-8'?>

<ItemGenerators>
  <ItemGenerator Name='Ranger clothes' DefaultImage='male_rangerClothing_forward0'
                 ItemType='clothes' GenderSpecific='true'>

    <Animations>
      <Animation animationName='male_rangerClothing_forward' direction='south' animIdx='walk'/>
      <Animation animationName='male_rangerClothing_back' direction='north' animIdx='walk'/>
      <Animation animationName='male_rangerClothing_left' direction='west' animIdx='walk'/>
      <Animation animationName='male_rangerClothing_right' direction='east' animIdx='walk'/>
    </Animations>
    <AlternativeAnimations>
      <Animation animationName='female_rangerClothing_forward' direction='south' animIdx='walk'/>
      <Animation animationName='female_rangerClothing_back' direction='north' animIdx='walk'/>
      <Animation animationName='female_rangerClothing_left' direction='west' animIdx='walk'/>
      <Animation animationName='female_rangerClothing_right' direction='east' animIdx='walk'/>
    </AlternativeAnimations>
  </ItemGenerator>
</ItemGenerators>